[1,0,0,[["cc.JsonAsset",["_name","json"],1]],[[0,0,1,3]],[[0,"PrivilegeConfig",{"1":{"name":"免广告","type":1,"systemid":0,"param":0,"val":0,"dec":"免广告"},"2":{"name":"获得钻石","type":1,"systemid":0,"param":0,"val":0,"dec":"立即获得钻石*688"},"3":{"name":"每日可领取%d陨铁","type":6,"systemid":1014,"param":1003,"val":388,"dec":"每日可领取陨铁*388"},"4":{"name":"每日福利金币领取次数+%d","type":2,"systemid":1018,"param":4,"val":1,"dec":"每日福利金币领取次数+1"},"5":{"name":"每日福利钻石领取次数+%d","type":2,"systemid":1018,"param":5,"val":1,"dec":"每日福利钻石领取次数+1"},"6":{"name":"每日福利经验领取次数+%d","type":2,"systemid":1018,"param":6,"val":1,"dec":"每日福利经验领取次数+1"},"7":{"name":"每日快速挂机次数+%d","type":3,"systemid":1006,"param":0,"val":1,"dec":"每日快速挂机次数+1"},"8":{"name":"挂机金币掉落+%d%%","type":4,"systemid":1006,"param":1001,"val":2500,"dec":"挂机金币掉落+25%"},"9":{"name":"挂机经验掉落+%d%%","type":5,"systemid":1006,"param":0,"val":2500,"dec":"挂机经验掉落+25%"},"10":{"name":"挂机玄铁掉落+%d%%","type":4,"systemid":1006,"param":1003,"val":2500,"dec":"挂机陨铁掉落+25%"},"11":{"name":"勋章额外增加%d经验","type":7,"systemid":1021,"param":0,"val":1,"dec":"勋章额外增加1点经验"},"12":{"name":"每日可领取%d钻石","type":6,"systemid":1014,"param":1002,"val":100,"dec":"每日可领取钻石*100"},"13":{"name":"每日可领取技能书","type":6,"systemid":1014,"param":2028,"val":20,"dec":"每日可领取技能书奋勇当先"},"14":{"name":"跳过战斗","type":8,"systemid":0,"param":0,"val":0,"dec":"跳过战斗"},"15":{"name":"加速锻造","type":9,"systemid":0,"param":0,"val":0,"dec":"加速锻造"},"16":{"name":"每日可领取%d陨铁","type":6,"systemid":1041,"param":1003,"val":1288,"dec":"每日可领取陨铁*1288"},"17":{"name":"每日可领取%d钻石","type":6,"systemid":1041,"param":1002,"val":588,"dec":"每日可领取钻石*588"},"18":{"name":"获得钻石","type":1,"systemid":0,"param":0,"val":0,"dec":"立即获得钻石*5888"},"19":{"name":"每日可领取诱饵","type":6,"systemid":1041,"param":1041,"val":5,"dec":"每日可领取诱饵*5"}}]],0,0,[],[],[]]
