[1,["1e0f31cc4@6c48a"],["_textureSource"],["cc.SpriteFrame"],0,[[[{"name":"ysdj3","rect":{"x":3,"y":3,"width":100,"height":100},"offset":{"x":0,"y":0},"originalSize":{"width":100,"height":100},"rotated":false,"capInsets":[0,0,0,0],"packable":true,"pixelsToUnit":100,"pivot":{"x":0.5,"y":0.5},"meshType":0}],[0],0,[0],[0],[0]],[[{"name":"ysdj5","rect":{"x":3,"y":109,"width":100,"height":100},"offset":{"x":0,"y":0},"originalSize":{"width":100,"height":100},"rotated":false,"capInsets":[0,0,0,0],"packable":true,"pixelsToUnit":100,"pivot":{"x":0.5,"y":0.5},"meshType":0}],[0],0,[0],[0],[0]],[[{"name":"ysdj4","rect":{"x":3,"y":215,"width":100,"height":100},"offset":{"x":0,"y":0},"originalSize":{"width":100,"height":100},"rotated":false,"capInsets":[0,0,0,0],"packable":true,"pixelsToUnit":100,"pivot":{"x":0.5,"y":0.5},"meshType":0}],[0],0,[0],[0],[0]],[[{"name":"ysdj1","rect":{"x":3,"y":321,"width":100,"height":100},"offset":{"x":0,"y":0},"originalSize":{"width":100,"height":100},"rotated":false,"capInsets":[0,0,0,0],"packable":true,"pixelsToUnit":100,"pivot":{"x":0.5,"y":0.5},"meshType":0}],[0],0,[0],[0],[0]]]]
